datasette_comments/__init__.py
datasette_comments/comment_parser.py
datasette_comments/hookspecs.py
datasette_comments/internal_migrations.py
datasette_comments/schema.sql
datasette_comments/static/content_script.min.js
datasette_comments/static/activity_view/index.min.css
datasette_comments/static/activity_view/index.min.js
datasette_comments/static/content_script/index.min.css
datasette_comments/static/content_script/index.min.js
datasette_comments/templates/activity_view.html
datasette_comments-0.1.0.dist-info/LICENSE
datasette_comments-0.1.0.dist-info/METADATA
datasette_comments-0.1.0.dist-info/WHEEL
datasette_comments-0.1.0.dist-info/entry_points.txt
datasette_comments-0.1.0.dist-info/top_level.txt
datasette_comments-0.1.0.dist-info/RECORD
