Metadata-Version: 2.1
Name: datasette-comments
Version: 0.1.0
Summary: A Datasette plugin for commenting on tables, rows, and values
Author: Alex Garcia
License: Apache-2.0
Project-URL: Homepage, https://github.com/datasette/datasette-comments
Project-URL: Changelog, https://github.com/datasette/datasette-comments/releases
Project-URL: Issues, https://github.com/datasette/datasette-comments/issues
Project-URL: CI, https://github.com/datasette/datasette-comments/actions
Classifier: License :: OSI Approved :: Apache Software License
License-File: LICENSE
Requires-Dist: datasette >=1.0a6
Requires-Dist: python-ulid
Requires-Dist: sqlite-migrate ==0.1b0
Provides-Extra: test
Requires-Dist: pytest ; extra == 'test'
Requires-Dist: pytest-asyncio ; extra == 'test'
Requires-Dist: pytest-playwright ; extra == 'test'
Requires-Dist: syrupy ; extra == 'test'
